pretix_capacity_reports/__init__.py
pretix_capacity_reports/apps.py
pretix_capacity_reports/exporter.py
pretix_capacity_reports/signals.py
pretix_capacity_reports/locale/de/LC_MESSAGES/django.mo
pretix_capacity_reports/locale/de/LC_MESSAGES/django.po
pretix_capacity_reports/locale/de_Informal/.gitkeep
pretix_capacity_reports/locale/de_Informal/LC_MESSAGES/django.mo
pretix_capacity_reports/locale/de_Informal/LC_MESSAGES/django.po
pretix_capacity_reports/static/pretix_capacity_reports/.gitkeep
pretix_capacity_reports/templates/pretix_capacity_reports/.gitkeep
pretix_capacity_reports-1.2.0.dist-info/LICENSE
pretix_capacity_reports-1.2.0.dist-info/METADATA
pretix_capacity_reports-1.2.0.dist-info/WHEEL
pretix_capacity_reports-1.2.0.dist-info/entry_points.txt
pretix_capacity_reports-1.2.0.dist-info/top_level.txt
pretix_capacity_reports-1.2.0.dist-info/RECORD
