Metadata-Version: 2.1
Name: pretix-capacity-reports
Version: 1.2.0
Summary: Capacity and utilization reports
Home-page: https://github.com/pretix-unofficial/pretix-capacity-reports
Author: pretix team
Author-email: support@pretix.eu
License: Apache
License-File: LICENSE
